Metadata-Version: 2.1
Name: prql
Version: 0.1.12
Summary: An interpreted relational query language that compiles to SQL
Home-page: https://github.com/erezsh/Preql
License: Interface-Protection Clause + MIT
Author: Erez Shin
Author-email: erezshin@gmail.com
Requires-Python: >=3.8,<4.0
Classifier: Development Status :: 3 - Alpha
Classifier: Environment :: Console
Classifier: Intended Audience :: Developers
Classifier: License :: Free To Use But Restricted
Classifier: License :: Other/Proprietary License
Classifier: Programming Language :: Python :: 3
Classifier: Programming Language :: Python :: 3.8
Classifier: Programming Language :: Python :: 3.9
Classifier: Topic :: Database :: Database Engines/Servers
Classifier: Topic :: Database :: Front-Ends
Classifier: Topic :: Software Development :: Compilers
Classifier: Topic :: Software Development :: Interpreters
Classifier: Topic :: Software Development :: Libraries :: Python Modules
Classifier: Typing :: Typed
Provides-Extra: mysql
Provides-Extra: pgsql
Provides-Extra: server
Requires-Dist: dsnparse
Requires-Dist: lark-parser (>=0.11.1,<0.12.0)
Requires-Dist: mysqlclient; extra == "mysql"
Requires-Dist: prompt-toolkit
Requires-Dist: psycopg2; extra == "pgsql"
Requires-Dist: pygments
Requires-Dist: rich
Requires-Dist: runtype (>=0.1.6,<0.2.0)
Requires-Dist: starlette; extra == "server"
Requires-Dist: tqdm
Project-URL: Documentation, https://preql.readthedocs.io/en/latest/
Project-URL: Repository, https://github.com/erezsh/Preql
